[
 {
  "connection_status": "Connected",
  "description": "Universal Robots MODBUS Simulator",
  "docstatus": 0,
  "doctype": "PLC Simulator",
  "enabled": 1,
  "equipment_type": "Robot",
  "io_points": [
   {
    "location_name": "Robot Mode",
    "modbus_address": 0,
    "parent": "UR Sim",
    "parentfield": "io_points",
    "parenttype": "PLC Simulator",
    "plc_address": "%IW0",
    "signal_type": "Analog Input Register",
    "toggle": 0,
    "value": "0"
   },
   {
    "location_name": "Robot Status Bits",
    "modbus_address": 0,
    "parent": "UR Sim",
    "parentfield": "io_points",
    "parenttype": "PLC Simulator",
    "plc_address": "%IX0.0",
    "signal_type": "Digital Input Contact",
    "toggle": 0,
    "value": "0"
   },
   {
    "location_name": "Safety Status",
    "modbus_address": 1,
    "parent": "UR Sim",
    "parentfield": "io_points",
    "parenttype": "PLC Simulator",
    "plc_address": "%IX0.1",
    "signal_type": "Digital Input Contact",
    "toggle": 0,
    "value": "1"
   },
   {
    "location_name": "Program Start",
    "modbus_address": 128,
    "parent": "UR Sim",
    "parentfield": "io_points",
    "parenttype": "PLC Simulator",
    "plc_address": "%QX16.0",
    "signal_type": "Digital Output Coil",
    "toggle": 0,
    "value": "0"
   },
   {
    "location_name": "Program Stop",
    "modbus_address": 129,
    "parent": "UR Sim",
    "parentfield": "io_points",
    "parenttype": "PLC Simulator",
    "plc_address": "%Qx16.1",
    "signal_type": "Digital Output Coil",
    "toggle": 0,
    "value": "0"
   },
   {
    "location_name": "Program Pause",
    "modbus_address": 130,
    "parent": "UR Sim",
    "parentfield": "io_points",
    "parenttype": "PLC Simulator",
    "plc_address": "%QX16.2",
    "signal_type": "Digital Output Coil",
    "toggle": 0,
    "value": "0"
   },
   {
    "location_name": "Tool Enable",
    "modbus_address": 200,
    "parent": "UR Sim",
    "parentfield": "io_points",
    "parenttype": "PLC Simulator",
    "plc_address": "%QX25.0",
    "signal_type": "Digital Output Coil",
    "toggle": 0,
    "value": "0"
   },
   {
    "location_name": "Digital Tool Out 0",
    "modbus_address": 201,
    "parent": "UR Sim",
    "parentfield": "io_points",
    "parenttype": "PLC Simulator",
    "plc_address": "%QX25.1",
    "signal_type": "Digital Output Coil",
    "toggle": 0,
    "value": "0"
   },
   {
    "location_name": "Digital Tool Out 1",
    "modbus_address": 202,
    "parent": "UR Sim",
    "parentfield": "io_points",
    "parenttype": "PLC Simulator",
    "plc_address": "%QX25.2",
    "signal_type": "Digital Output Coil",
    "toggle": 0,
    "value": "0"
   },
   {
    "location_name": "Digital Tool In 0",
    "modbus_address": 200,
    "parent": "UR Sim",
    "parentfield": "io_points",
    "parenttype": "PLC Simulator",
    "plc_address": "%IX25.0",
    "signal_type": "Digital Input Contact",
    "toggle": 0,
    "value": "0"
   },
   {
    "location_name": "Digital Tool In 1",
    "modbus_address": 201,
    "parent": "UR Sim",
    "parentfield": "io_points",
    "parenttype": "PLC Simulator",
    "plc_address": "%IX25.1",
    "signal_type": "Digital Input Contact",
    "toggle": 0,
    "value": "0"
   },
   {
    "location_name": "TCP X Position",
    "modbus_address": 400,
    "parent": "UR Sim",
    "parentfield": "io_points",
    "parenttype": "PLC Simulator",
    "plc_address": "%IW400",
    "signal_type": "Analog Input Register",
    "toggle": 0,
    "value": "0"
   },
   {
    "location_name": "TCP Y Position",
    "modbus_address": 401,
    "parent": "UR Sim",
    "parentfield": "io_points",
    "parenttype": "PLC Simulator",
    "plc_address": "%IW401",
    "signal_type": "Analog Input Register",
    "toggle": 0,
    "value": "0"
   },
   {
    "location_name": "TCP Z Position",
    "modbus_address": 402,
    "parent": "UR Sim",
    "parentfield": "io_points",
    "parenttype": "PLC Simulator",
    "plc_address": "%IW402",
    "signal_type": "Analog Input Register",
    "toggle": 0,
    "value": "0"
   }
  ],
  "last_status_update": "2024-12-20 17:00:55.233739",
  "modified": "2024-12-20 17:50:11.798889",
  "name": "UR Sim",
  "server_port": 502,
  "simulator_name": "UR Sim"
 }
]